LICENSE
MANIFEST.in
setup.py
Rider.egg-info/PKG-INFO
Rider.egg-info/SOURCES.txt
Rider.egg-info/dependency_links.txt
Rider.egg-info/requires.txt
Rider.egg-info/top_level.txt
docs/Makefile
docs/conf.py
docs/deployment.rst
docs/index.rst
docs/installation.rst
docs/management.rst
docs/routes.rst
docs/views.rst
docs/build/.buildinfo
docs/build/deployment.html
docs/build/genindex.html
docs/build/index.html
docs/build/installation.html
docs/build/management.html
docs/build/objects.inv
docs/build/routes.html
docs/build/search.html
docs/build/searchindex.js
docs/build/views.html
docs/build/.doctrees/deployment.doctree
docs/build/.doctrees/environment.pickle
docs/build/.doctrees/index.doctree
docs/build/.doctrees/installation.doctree
docs/build/.doctrees/management.doctree
docs/build/.doctrees/routes.doctree
docs/build/.doctrees/views.doctree
docs/build/.doctrees/env/lib/python2.7/site-packages/Pygments-2.0.1.dist-info/DESCRIPTION.doctree
docs/build/.doctrees/env/lib/python2.7/site-packages/Sphinx-1.2.3.dist-info/DESCRIPTION.doctree
docs/build/.doctrees/env/lib/python2.7/site-packages/pip-1.5.4.dist-info/DESCRIPTION.doctree
docs/build/.doctrees/env/lib/python2.7/site-packages/setuptools-2.2.dist-info/DESCRIPTION.doctree
docs/build/.doctrees/env/lib/python2.7/site-packages/sphinx/ext/autosummary/templates/autosummary/base.doctree
docs/build/.doctrees/env/lib/python2.7/site-packages/sphinx/ext/autosummary/templates/autosummary/class.doctree
docs/build/.doctrees/env/lib/python2.7/site-packages/sphinx/ext/autosummary/templates/autosummary/module.doctree
docs/build/.doctrees/env/lib/python2.7/site-packages/tests/roots/test-only-directive/contents.doctree
docs/build/.doctrees/env/lib/python2.7/site-packages/tests/roots/test-only-directive/only.doctree
docs/build/.doctrees/env/local/lib/python2.7/site-packages/Pygments-2.0.1.dist-info/DESCRIPTION.doctree
docs/build/.doctrees/env/local/lib/python2.7/site-packages/Sphinx-1.2.3.dist-info/DESCRIPTION.doctree
docs/build/.doctrees/env/local/lib/python2.7/site-packages/pip-1.5.4.dist-info/DESCRIPTION.doctree
docs/build/.doctrees/env/local/lib/python2.7/site-packages/setuptools-2.2.dist-info/DESCRIPTION.doctree
docs/build/.doctrees/env/local/lib/python2.7/site-packages/sphinx/ext/autosummary/templates/autosummary/base.doctree
docs/build/.doctrees/env/local/lib/python2.7/site-packages/sphinx/ext/autosummary/templates/autosummary/class.doctree
docs/build/.doctrees/env/local/lib/python2.7/site-packages/sphinx/ext/autosummary/templates/autosummary/module.doctree
docs/build/.doctrees/env/local/lib/python2.7/site-packages/tests/roots/test-only-directive/contents.doctree
docs/build/.doctrees/env/local/lib/python2.7/site-packages/tests/roots/test-only-directive/only.doctree
docs/build/_sources/deployment.txt
docs/build/_sources/index.txt
docs/build/_sources/installation.txt
docs/build/_sources/management.txt
docs/build/_sources/routes.txt
docs/build/_sources/env/lib/python2.7/site-packages/Pygments-2.0.1.dist-info/DESCRIPTION.txt
docs/build/_sources/env/lib/python2.7/site-packages/Sphinx-1.2.3.dist-info/DESCRIPTION.txt
docs/build/_sources/env/lib/python2.7/site-packages/pip-1.5.4.dist-info/DESCRIPTION.txt
docs/build/_sources/env/lib/python2.7/site-packages/setuptools-2.2.dist-info/DESCRIPTION.txt
docs/build/_sources/env/local/lib/python2.7/site-packages/Pygments-2.0.1.dist-info/DESCRIPTION.txt
docs/build/_sources/env/local/lib/python2.7/site-packages/Sphinx-1.2.3.dist-info/DESCRIPTION.txt
docs/build/_sources/env/local/lib/python2.7/site-packages/pip-1.5.4.dist-info/DESCRIPTION.txt
docs/build/_sources/env/local/lib/python2.7/site-packages/setuptools-2.2.dist-info/DESCRIPTION.txt
docs/build/env/lib/python2.7/site-packages/Pygments-2.0.1.dist-info/DESCRIPTION.html
docs/build/env/lib/python2.7/site-packages/Sphinx-1.2.3.dist-info/DESCRIPTION.html
docs/build/env/lib/python2.7/site-packages/pip-1.5.4.dist-info/DESCRIPTION.html
docs/build/env/lib/python2.7/site-packages/setuptools-2.2.dist-info/DESCRIPTION.html
docs/build/env/local/lib/python2.7/site-packages/Pygments-2.0.1.dist-info/DESCRIPTION.html
docs/build/env/local/lib/python2.7/site-packages/Sphinx-1.2.3.dist-info/DESCRIPTION.html
docs/build/env/local/lib/python2.7/site-packages/pip-1.5.4.dist-info/DESCRIPTION.html
docs/build/env/local/lib/python2.7/site-packages/setuptools-2.2.dist-info/DESCRIPTION.html
